<?xml version="1.0" encoding="UTF-8"?><extraction><clueid>90118556</clueid><fullpath><![CDATA[http://www.tuniu.com/guide/d-shanghai-2500/jingdian/22/]]></fullpath><theme>tuniu1</theme><middle>default</middle><baseURI><bucketBaseURI><bucketName>scenic</bucketName><uri><![CDATA[http://www.tuniu.com/guide/d-shanghai-2500/jingdian/22/]]></uri></bucketBaseURI></baseURI>
<scenic><item><scenicaddress>上海市青浦区北淀浦河路</scenicaddress><scenicname>万寿塔</scenicname></item><item><scenicaddress>"上海市青浦区朱家角镇西井街127-129号(课植园旁)</scenicaddress><scenicname>朱家角</scenicname></item><item><scenicaddress>上海市青浦区白鹤乡青龙村</scenicaddress><scenicname>青龙塔</scenicname></item><item><scenicaddress>上海青浦区公园路612号(近青安路)</scenicaddress><scenicname>曲水园</scenicname></item><item><scenicaddress>上海市浦东新区浦东大道2175弄88号</scenicaddress><scenicname>杨浦大桥</scenicname></item><item><scenicaddress>上海市长宁区新华路160号(番禺路口)</scenicaddress><scenicname>上海影城</scenicname></item><item><scenicaddress>上海市长宁区虹桥路1660号</scenicaddress><scenicname>刘海粟美术馆</scenicname></item><item><scenicaddress>上海市长宁区宋园路21号</scenicaddress><scenicname>宋庆龄陵园</scenicname></item><item><scenicaddress>上海市长宁区虹桥路2381号(近虹井路)</scenicaddress><scenicname>上海动物园</scenicname></item><item><scenicaddress>上海市水城南路荣华东道96号维多利亚大厦c座裙房2楼</scenicaddress><scenicname>古北新区</scenicname></item><item><scenicaddress>上海市宝山区武威东路76号</scenicaddress><scenicname>陶行知纪念馆</scenicname></item><item><scenicaddress>上海市宝山区吴淞塘后路68号（近淞宝路）</scenicaddress><scenicname>海军上海博览馆</scenicname></item><item><scenicaddress>中国上海市宝山区友谊路1号</scenicaddress><scenicname>临江公园</scenicname></item><item><scenicaddress>上海市宝山区境内</scenicaddress><scenicname>宝山工业旅游区</scenicname></item><item><scenicaddress>上海普陀区兰溪路399号(近南大街)</scenicaddress><scenicname>真如寺</scenicname></item><item><scenicaddress>普陀区安远路170号</scenicaddress><scenicname>玉佛寺</scenicname></item><item><scenicaddress>上海市大渡河路189号</scenicaddress><scenicname>长风公园</scenicname></item><item><scenicaddress>上海市卢湾区太仓路181弄</scenicaddress><scenicname>新天地</scenicname></item></scenic></extraction>