<?xml version="1.0" encoding="UTF-8"?><extraction><clueid>90117645</clueid><fullpath><![CDATA[http://you.ctrip.com/sight/shanghai2/s0-p14.html]]></fullpath><theme>xiecheng1</theme><middle>default</middle><baseURI><bucketBaseURI><bucketName>景点</bucketName><uri><![CDATA[http://you.ctrip.com/sight/shanghai2/s0-p14.html#sightname]]></uri></bucketBaseURI></baseURI>
<scenic><item><scenicaddress>
上海市嘉定区塔城路299号                        </scenicaddress><scenicname>汇龙潭公园</scenicname></item><item><scenicaddress>
上海市静安区南京西路1649号                        </scenicaddress><scenicname>静安公园</scenicname></item><item><scenicaddress>
上海市浦东新区惠南镇北门路289号                        </scenicaddress><scenicname>南汇桃源民俗村</scenicname></item><item><scenicaddress>
上海市奉贤区海湾路奉新路9号                        </scenicaddress><scenicname>奉贤海湾旅游区</scenicname></item><item><scenicaddress>
上海市青浦区练塘镇朱枫公路3516号（近下塘街）                        </scenicaddress><scenicname>陈云纪念馆</scenicname></item><item><scenicaddress>
上海市徐汇区龙华西路180号                        </scenicaddress><scenicname>龙华烈士陵园</scenicname></item><item><scenicaddress>
上海市青浦区西南角，邻接昆山市                        </scenicaddress><scenicname>淀山湖风景区</scenicname></item><item><scenicaddress>
上海市黄浦区泰康路25号                        </scenicaddress><scenicname>上海琉璃艺术博物馆</scenicname></item><item><scenicaddress>
上海市普陀区真光路1288号百联中环购物广场C区地下室                        </scenicaddress><scenicname>飞霆卡丁车馆</scenicname></item><item><scenicaddress>
上海市崇明县吴淞口外                        </scenicaddress><scenicname>长兴岛</scenicname></item><item><scenicaddress>
上海市徐汇区南丹路17号                        </scenicaddress><scenicname>徐光启墓园</scenicname></item><item><scenicaddress>
上海市黄浦区中山东一路500号                        </scenicaddress><scenicname>外滩情人墙</scenicname></item><item><scenicaddress>
上海市静安区茂名北路120弄5-9号                         </scenicaddress><scenicname>毛泽东旧居</scenicname></item><item><scenicaddress>
上海市浦东新区丁香路425号上海东方艺术中心内4层                        </scenicaddress><scenicname>八音盒珍品陈列馆</scenicname></item><item><scenicaddress>
上海市徐汇区汾阳路79号                        </scenicaddress><scenicname>上海工艺美术博物馆</scenicname></item></scenic></extraction>