<?xml version="1.0" encoding="utf-8" ?> 
<PlaceSearchResponse> 
  <status>0</status>
  <message>ok</message>
  	<total>5</total>
    <results>
			<result>
			<name>中国民主促进会旧址</name>
			<location>
				<lat>31.214908</lat>
				<lng>121.468621</lng>
			</location>
							<address>绍兴路108号</address>
										<telephone>(021)64370835</telephone>
										<uid>38e480371d6deb4a373a7106</uid>
								</result>
			<result>
			<name>中国民主促进会成立旧址</name>
			<location>
				<lat>31.21507</lat>
				<lng>121.468279</lng>
			</location>
							<address>卢湾区陕西南路235号（近淮海中路）</address>
													<uid>402e1777cc6ca87d96ca07d8</uid>
								</result>
			<result>
			<name>中国民主促进会旧址-西门</name>
			<location>
				<lat>31.215039</lat>
				<lng>121.468278</lng>
			</location>
							<address>陕西南路235</address>
													<uid>0a264b65b96e98c59cec2b8f</uid>
								</result>
			<result>
			<name>中国民主促进会旧址-南门</name>
			<location>
				<lat>31.21483</lat>
				<lng>121.468628</lng>
			</location>
							<address>绍兴路108号</address>
													<uid>a7ffcde575753a4b2eb90848</uid>
								</result>
			<result>
			<name>中国民主促进会旧址-西一门</name>
			<location>
				<lat>31.215332</lat>
				<lng>121.468278</lng>
			</location>
							<address>陕西南路235号附近</address>
													<uid>cc20cd2bbd982be01ce99997</uid>
								</result>
	  </results>
</PlaceSearchResponse>
