<?xml version="1.0" encoding="utf-8" ?> 
<PlaceSearchResponse> 
  <status>0</status>
  <message>ok</message>
  	<total>12</total>
    <results>
			<result>
			<name>佘山索道</name>
			<location>
				<lat>31.100956</lat>
				<lng>121.203251</lng>
			</location>
							<address>外青松公路佘山索道附近</address>
													<uid>dfcd74cfa3f4f5d54d2fdfe0</uid>
								</result>
			<result>
			<name>上海欢乐谷电子门票（松江店）</name>
			<location>
				<lat>31.099974</lat>
				<lng>121.22625</lng>
			</location>
							<address>上海市松江区佘山镇林湖路888号欢乐谷(都市路友情路)</address>
										<telephone>(021)33552222</telephone>
										<uid>cac5fc76735bee8d2cb96d1c</uid>
								</result>
			<result>
			<name>索道饭店(环山路)</name>
			<location>
				<lat>31.100956</lat>
				<lng>121.203296</lng>
			</location>
							<address>外青松公路佘山索道附近</address>
													<uid>ff1828ce6ae626882b201ab6</uid>
								</result>
			<result>
			<name>佘山索道商店</name>
			<location>
				<lat>31.100979</lat>
				<lng>121.203215</lng>
			</location>
							<address>外青松公路佘山索道附近</address>
													<uid>3bd2b28de02764fdd3ff23ed</uid>
								</result>
			<result>
			<name>索道饭店(上海市地震局佘山地震基准台西北)</name>
			<location>
				<lat>31.100778</lat>
				<lng>121.203664</lng>
			</location>
							<address>上海天文博物馆附近</address>
													<uid>a324b50291021e126fc02ce6</uid>
								</result>
			<result>
			<name>佘山滑索道</name>
			<location>
				<lat>31.105957</lat>
				<lng>121.20282</lng>
			</location>
							<address>东佘山北侧</address>
										<telephone>(021)57652794</telephone>
										<uid>2ad32cc314d5488e9c95dea6</uid>
								</result>
			<result>
			<name>索道饭店</name>
			<location>
				<lat>31.100778</lat>
				<lng>121.203501</lng>
			</location>
							<address>上海市松江区佘山三角街</address>
										<telephone>(021)57652556</telephone>
										<uid>2cd81d51b1b1b0d415a1909e</uid>
								</result>
			<result>
			<name>欣峰佘山人家</name>
			<location>
				<lat>31.100716</lat>
				<lng>121.203763</lng>
			</location>
							<address>上海松江区松江佘山旅游度假区西佘山索道附近(近森林宾馆)</address>
										<telephone>13472590660,(021)57653664</telephone>
										<uid>b2084b015136a22147572695</uid>
								</result>
			<result>
			<name>茶酒楼</name>
			<location>
				<lat>31.100824</lat>
				<lng>121.203583</lng>
			</location>
							<address>外青松公路佘山索道附近</address>
													<uid>6f6ffb7da201659983a00c6e</uid>
								</result>
			<result>
			<name>林青水果</name>
			<location>
				<lat>31.100863</lat>
				<lng>121.203512</lng>
			</location>
							<address>外青松公路佘山索道附近</address>
													<uid>b365d3b08fcd2245f03cbadf</uid>
								</result>
	  </results>
</PlaceSearchResponse>
