<?xml version="1.0" encoding="utf-8" ?> 
<PlaceSearchResponse> 
  <status>0</status>
  <message>ok</message>
  	<total>8</total>
    <results>
			<result>
			<name>永清苑</name>
			<location>
				<lat>31.394646</lat>
				<lng>121.499689</lng>
			</location>
							<address>宝山区双城路234号(双城路淞宝路)</address>
													<uid>cc788fde3ba8eb8b88fc067c</uid>
								</result>
			<result>
			<name>永清苑</name>
			<location>
				<lat>31.398137</lat>
				<lng>121.505125</lng>
			</location>
							<address>宝山区双城路234号（双城路淞宝路）</address>
													<uid>3129b90b8b5c879895f08c00</uid>
								</result>
			<result>
			<name>永清苑网吧</name>
			<location>
				<lat>31.290318</lat>
				<lng>121.429157</lng>
			</location>
							<address>沪太支路180号2楼</address>
													<uid>46bc215f20453c42e115f9ce</uid>
								</result>
			<result>
			<name>永清苑-北门</name>
			<location>
				<lat>31.395309</lat>
				<lng>121.499068</lng>
			</location>
							<address>双城路490号</address>
										<telephone>(021)56674264</telephone>
										<uid>e5619aad15202ebb1d1d1167</uid>
								</result>
			<result>
			<name>永清苑-东门</name>
			<location>
				<lat>31.394669</lat>
				<lng>121.500721</lng>
			</location>
							<address>永清苑</address>
													<uid>b533ea4a4a50353c4f6d4606</uid>
								</result>
			<result>
			<name>永清苑网络会所</name>
			<location>
				<lat>31.290318</lat>
				<lng>121.429128</lng>
			</location>
							<address>宝山区沪太支路180号2楼</address>
													<uid>19f09da4623ae6db88b988ae</uid>
								</result>
			<result>
			<name>上海工程管理学院</name>
			<location>
				<lat>31.394469</lat>
				<lng>121.499882</lng>
			</location>
							<address>上海市宝山区永清苑</address>
										<telephone>(021)52130244</telephone>
										<uid>0f305550292b3a0021026243</uid>
								</result>
			<result>
			<name>新景旅馆</name>
			<location>
				<lat>31.394338</lat>
				<lng>121.498497</lng>
			</location>
							<address>上海宝山区牡丹江路726号（永清苑对面）</address>
										<telephone>(021)56176533</telephone>
										<uid>447992e424a8af513310af3a</uid>
								</result>
	  </results>
</PlaceSearchResponse>
