<?xml version="1.0" encoding="utf-8" ?> 
<PlaceSearchResponse> 
  <status>0</status>
  <message>ok</message>
  	<total>2</total>
    <results>
			<result>
			<name>金桥镇市民文化广场</name>
			<location>
				<lat>31.272981</lat>
				<lng>121.616115</lng>
			</location>
							<address>金桥镇市民文化广场(西门)附近</address>
													<uid>c257333814e4061807026f42</uid>
								</result>
			<result>
			<name>金桥镇市民文化广场-西门</name>
			<location>
				<lat>31.271045</lat>
				<lng>121.618026</lng>
			</location>
							<address>上海市浦东新区</address>
													<uid>f76ea2e40309a57ceb1e9756</uid>
								</result>
	  </results>
</PlaceSearchResponse>
