<?xml version="1.0" encoding="UTF-8"?><extraction><clueid>90118474</clueid><fullpath><![CDATA[http://www.mafengwo.cn/jd/10099/0-0-0-0-0-30.html]]></fullpath><theme>mafengwo111</theme><middle>default</middle><baseURI><bucketBaseURI><bucketName>scenic</bucketName><uri><![CDATA[http://www.mafengwo.cn/jd/10099/0-0-0-0-0-30.html]]></uri></bucketBaseURI></baseURI>
<scenic><item><secnicname>小红楼</secnicname></item><item><secnicname>黎安公园</secnicname></item><item><secnicname>申隆生态园</secnicname></item><item><secnicname>新天安堂</secnicname></item><item><secnicname>黄浦大境关帝庙</secnicname></item><item><secnicname>上海纺织博物馆</secnicname></item><item><secnicname>强生浦江游览</secnicname></item><item><secnicname>上海临港新城展示中心</secnicname></item><item><secnicname>愚园路</secnicname></item><item><secnicname>大团桃园</secnicname></item><item><secnicname>松江唐经幢</secnicname></item><item><secnicname>华山路</secnicname></item><item><secnicname>外滩情人墙</secnicname></item><item><secnicname>长兴岛</secnicname></item><item><secnicname>豆香园</secnicname></item></scenic></extraction>