<?xml version="1.0" encoding="UTF-8"?><extraction><clueid>90118556</clueid><fullpath><![CDATA[http://www.tuniu.com/guide/d-shanghai-2500/jingdian/19/]]></fullpath><theme>tuniu1</theme><middle>default</middle><baseURI><bucketBaseURI><bucketName>scenic</bucketName><uri><![CDATA[http://www.tuniu.com/guide/d-shanghai-2500/jingdian/19/]]></uri></bucketBaseURI></baseURI>
<scenic><item><scenicaddress>上海市墨玉路267号</scenicaddress><scenicname>安亭</scenicname></item><item><scenicaddress>上海市青浦区朱家角镇西湖街35号(近漕平路)</scenicaddress><scenicname>大清邮局</scenicname></item><item><scenicaddress>上海市黄浦区南京东路20号</scenicaddress><scenicname>和平饭店</scenicname></item><item><scenicaddress>浦东新区滨江大道2789号</scenicaddress><scenicname>外滩观光隧道</scenicname></item><item><scenicaddress>从东方明珠至浦东世纪公园全长约55公里</scenicaddress><scenicname>世纪大道</scenicname></item><item><scenicaddress>上海市黄浦区沉香阁路29号(近福佑路)</scenicaddress><scenicname>沉香阁</scenicname></item><item><scenicaddress>上海市卢湾区东昌路1号</scenicaddress><scenicname>黄浦江</scenicname></item><item><scenicaddress>上海浦东新区华夏东路6015号（东首海滨广场）。</scenicaddress><scenicname>三甲港</scenicname></item><item><scenicaddress>上海市松江区中山东路235号</scenicaddress><scenicname>方塔园</scenicname></item><item><scenicaddress>上海市南京西路1376号商城西峰301室</scenicaddress><scenicname>英国驻上海总领事馆</scenicname></item><item><scenicaddress>上海市崇明县</scenicaddress><scenicname>南门景观大堤</scenicname></item><item><scenicaddress>上海市黄浦区邑城路1号</scenicaddress><scenicname>上海城隍庙</scenicname></item><item><scenicaddress>上海市黄浦区安仁街132号(城隍庙内 ）</scenicaddress><scenicname>豫园</scenicname></item><item><scenicaddress>上海市黄浦区南马路1410号</scenicaddress><scenicname>南浦大桥</scenicname></item><item><scenicaddress>上海市静安区奉贤路272号（近南京西路江宁路）</scenicaddress><scenicname>天蟾逸夫舞台</scenicname></item><item><scenicaddress>上海市黄浦区黄陂北路286号</scenicaddress><scenicname>上海大剧院</scenicname></item><item><scenicaddress>上海市黄浦区人民大道201号(近武胜路)</scenicaddress><scenicname>上海博物馆</scenicname></item><item><scenicaddress>上海市黄浦区</scenicaddress><scenicname>人民广场</scenicname></item></scenic></extraction>