<?xml version="1.0" encoding="UTF-8"?><extraction><clueid>90117645</clueid><fullpath><![CDATA[http://you.ctrip.com/sight/shanghai2/s0-p52.html]]></fullpath><theme>xiecheng1</theme><middle>default</middle><baseURI><bucketBaseURI><bucketName>景点</bucketName><uri><![CDATA[http://you.ctrip.com/sight/shanghai2/s0-p52.html#sightname]]></uri></bucketBaseURI></baseURI>
<scenic><item><scenicaddress>
上海市杨浦区长阳路368号                        </scenicaddress><scenicname>中国现代国之宝艺术馆</scenicname></item><item><scenicaddress>
上海市杨浦区杨树浦路1426号海救大楼2楼                        </scenicaddress><scenicname>中国救捞博物馆</scenicname></item><item><scenicaddress>
上海市普陀区大渡河路1894号（近铜川路）                        </scenicaddress><scenicname>真如公园</scenicname></item><item><scenicaddress>
上海市长宁区长宁路2028号                        </scenicaddress><scenicname>虹桥河滨公园</scenicname></item><item><scenicaddress>
上海市杨浦区控江路261号                        </scenicaddress><scenicname>内江公园</scenicname></item><item><scenicaddress>
上海市金山区花贤路44号                        </scenicaddress><scenicname>张堰公园</scenicname></item><item><scenicaddress>
上海市静安区西康路255号                        </scenicaddress><scenicname>西康公园</scenicname></item><item><scenicaddress>
上海市嘉定区新黄路40号                        </scenicaddress><scenicname>黄渡公园</scenicname></item><item><scenicaddress>
上海市长宁区水城路735号                        </scenicaddress><scenicname>天原公园</scenicname></item><item><scenicaddress>
上海市闸北区场中路2150号                        </scenicaddress><scenicname>彭浦公园</scenicname></item><item><scenicaddress>
上海市杨浦区包头路929号                        </scenicaddress><scenicname>工农公园</scenicname></item><item><scenicaddress>
上海市杨浦区惠民路724号                        </scenicaddress><scenicname>惠民公园</scenicname></item><item><scenicaddress>
上海市杨浦区平凉路1738号                        </scenicaddress><scenicname>平凉公园</scenicname></item><item><scenicaddress>
上海市徐汇区华泾路858号                        </scenicaddress><scenicname>宁国禅寺</scenicname></item><item><scenicaddress>
上海市浦东新区华夏西路399号中环上中路隧道（耀龙路出口）                        </scenicaddress><scenicname>法华学问寺</scenicname></item></scenic></extraction>